{
  "_id": "dqa-en-117-c0032",
  "level": 1,
  "novel_id": 117,
  "title": "阳光下的罪恶",
  "source_file": "data\\raw\\detectiveqa\\novel_data_en\\117-阳光下的罪恶-阿加莎克里斯蒂.txt",
  "chunk_index": 32,
  "summary": "Hercule Poirot reveals his investigation into the murder of Eleanor Marshall, beginning with the evidence found in the room of her stepdaughter, Linda Marshall. Poirot presents findings of melted wax, burnt hair, and a book on witchcraft, suggesting Linda may have performed a superstitious ritual using a wax effigy and a needle to express a desire to kill. He notes that Linda's alibi relies on time evidence she provided herself and suggests she possessed the physical strength to have traveled from the mountain to the beach to strangle Eleanor.\n\nWhen Kenneth Marshall insists on his wife's innocence, Poirot explores alternative motives such as blackmail, drug trafficking, or religious fanaticism. He proposes that Kenneth might have committed the murder with an accomplice who typed a forged letter in his room to provide an alibi. Poirot exposes that Kenneth and Rosamund Darnley lied about their whereabouts and the positioning of a typewriter to cover their actions.\n\nFinally, Poirot turns his attention to Patrick Redfern. He argues that Eleanor Marshall went to Elfrida Bay to meet a lover, believing it to be Patrick, and that Patrick killed her after she emerged from a hiding spot. Poirot reveals that the \"body\" seen by witnesses was actually Patrick's accomplice, Christine, who had been painted black and was wearing a paper hat to impersonate the corpse. Poirot identifies Patrick and Christine as Edward and Christine Corey, noting they were recognized by police from a guest photograph following their involvement in the previous murder of Alice Corey.",
  "summary_whitespace_tokens": 250,
  "start_paragraph_id": 1982,
  "end_paragraph_id": 2014,
  "paragraph_ids": [
    1982,
    1983,
    1984,
    1985,
    1986,
    1987,
    1988,
    1989,
    1990,
    1991,
    1992,
    1993,
    1994,
    1995,
    1996,
    1997,
    1998,
    1999,
    2000,
    2001,
    2002,
    2003,
    2004,
    2005,
    2006,
    2007,
    2008,
    2009,
    2010,
    2011,
    2012,
    2013,
    2014
  ],
  "paragraph_doc_ids": [
    "dqa-en-117-p1982",
    "dqa-en-117-p1983",
    "dqa-en-117-p1984",
    "dqa-en-117-p1985",
    "dqa-en-117-p1986",
    "dqa-en-117-p1987",
    "dqa-en-117-p1988",
    "dqa-en-117-p1989",
    "dqa-en-117-p1990",
    "dqa-en-117-p1991",
    "dqa-en-117-p1992",
    "dqa-en-117-p1993",
    "dqa-en-117-p1994",
    "dqa-en-117-p1995",
    "dqa-en-117-p1996",
    "dqa-en-117-p1997",
    "dqa-en-117-p1998",
    "dqa-en-117-p1999",
    "dqa-en-117-p2000",
    "dqa-en-117-p2001",
    "dqa-en-117-p2002",
    "dqa-en-117-p2003",
    "dqa-en-117-p2004",
    "dqa-en-117-p2005",
    "dqa-en-117-p2006",
    "dqa-en-117-p2007",
    "dqa-en-117-p2008",
    "dqa-en-117-p2009",
    "dqa-en-117-p2010",
    "dqa-en-117-p2011",
    "dqa-en-117-p2012",
    "dqa-en-117-p2013",
    "dqa-en-117-p2014"
  ],
  "source_whitespace_tokens": 1524,
  "source_character_count": 8572,
  "source_sha256": "075b27035c36089972cb008d0df87046bba8cbaa2545d1d234c4026df052bd6d",
  "request_sha256": "6b6b04b8d5ae0b4123da8240eb1f526fa6224b6cbdb184a4951526f0cd146316",
  "model": "gemma-4-26b-a4b-it",
  "temperature": 0.2,
  "seed": 42,
  "max_output_tokens": 5000,
  "prompt_version": "detectiveqa-summary-pass2-v1.1-fair",
  "pass2_method": "previous_pass2_current_pass1_global_pass1",
  "pass1_prompt_version": "detectiveqa-summary-v1.2",
  "pass1_model": "gemma-4-26b-a4b-it",
  "pass1_summary_sha256": "eb11c1ef4446886029768b985e77e6d1f70c7062c9ce3474c69d88375dc602b9",
  "previous_pass2_summary_sha256": "f68608639254dacb746b773b61c7e38949290b68e37061c751681a99b038c415",
  "global_pass1_summary_sha256": "81fd1d8a207054d18382ab958da9d045cfac073b2c286a92ea3bb7925a561200"
}
