{
  "_id": "dqa-en-137-c0018",
  "level": 1,
  "novel_id": 137,
  "title": "破镜谋杀案",
  "source_file": "data\\raw\\detectiveqa\\novel_data_en\\137-破镜谋杀案-阿加莎克里斯蒂.txt",
  "chunk_index": 18,
  "summary": "Jason Radcliffe explains to Chief Inspector Craddock and Detective Dumot why he remained silent regarding his suspicion that his wife, Marina, was the intended target of a poisoning attempt. Radcliffe admits he believes someone intended to administer a fatal dose of poison to Marina in a public setting, a method that would make prosecution difficult due to the presence of many strangers. He chose to withhold this information to protect Marina’s fragile mental state. He describes her as an actress who seeks constant security but has faced repeated tragedies, including the birth of a son with intellectual disabilities eleven years prior, which resulted in her hospitalization in a sanatorium. Radcliffe notes that Marina had recently regained a sense of calm and optimism, and he feared that informing her of the threat would cause her to collapse again.\n\nWhen questioned about suspects, Radcliffe refuses to name anyone, stating that while the evidence of an attempted murder is factual, he finds it unbelievable that someone would hate Marina so much. He recounts the events at his home, where he poured two glasses of gin from a pitcher—one for Marina and one for Mrs. Bardok. During the event, while guests including the mayor and movie company representatives were milling around, the drinks were left on a table. Radcliffe believes the poison was added to Marina's glass during this time. The attempt failed when Mrs. Bardok accidentally dropped her glass, and Marina insisted that Mrs. Bardok drink from Marina's glass instead. Mrs. Bardok died four to five minutes after consuming the liquid.",
  "summary_whitespace_tokens": 258,
  "start_paragraph_id": 1027,
  "end_paragraph_id": 1057,
  "paragraph_ids": [
    1027,
    1028,
    1029,
    1030,
    1031,
    1032,
    1033,
    1034,
    1035,
    1036,
    1037,
    1038,
    1039,
    1040,
    1041,
    1042,
    1043,
    1044,
    1045,
    1046,
    1047,
    1048,
    1049,
    1050,
    1051,
    1052,
    1053,
    1054,
    1055,
    1056,
    1057
  ],
  "paragraph_doc_ids": [
    "dqa-en-137-p1027",
    "dqa-en-137-p1028",
    "dqa-en-137-p1029",
    "dqa-en-137-p1030",
    "dqa-en-137-p1031",
    "dqa-en-137-p1032",
    "dqa-en-137-p1033",
    "dqa-en-137-p1034",
    "dqa-en-137-p1035",
    "dqa-en-137-p1036",
    "dqa-en-137-p1037",
    "dqa-en-137-p1038",
    "dqa-en-137-p1039",
    "dqa-en-137-p1040",
    "dqa-en-137-p1041",
    "dqa-en-137-p1042",
    "dqa-en-137-p1043",
    "dqa-en-137-p1044",
    "dqa-en-137-p1045",
    "dqa-en-137-p1046",
    "dqa-en-137-p1047",
    "dqa-en-137-p1048",
    "dqa-en-137-p1049",
    "dqa-en-137-p1050",
    "dqa-en-137-p1051",
    "dqa-en-137-p1052",
    "dqa-en-137-p1053",
    "dqa-en-137-p1054",
    "dqa-en-137-p1055",
    "dqa-en-137-p1056",
    "dqa-en-137-p1057"
  ],
  "source_whitespace_tokens": 1601,
  "source_character_count": 9013,
  "source_sha256": "3fc4553998ee7d1a9678b76d6b783be92ad1a5235fd715665bbd37e9659b07d0",
  "request_sha256": "08906038ee324f4c0532ebdb1cb5409940dacb7b7c00368fe573e7558ad05f82",
  "model": "gemma-4-26b-a4b-it",
  "temperature": 0.2,
  "seed": 42,
  "max_output_tokens": 5000,
  "prompt_version": "detectiveqa-summary-pass2-v1.1-fair",
  "pass2_method": "previous_pass2_current_pass1_global_pass1",
  "pass1_prompt_version": "detectiveqa-summary-v1.2",
  "pass1_model": "gemma-4-26b-a4b-it",
  "pass1_summary_sha256": "c81879d91433b1f9a75732c6e9aacea2b87f59242e5512b7e449e8910e74c19e",
  "previous_pass2_summary_sha256": "91b1731170153841f2b2e609da4c2452aa36920aa6935e18d34d55549d3dcedb",
  "global_pass1_summary_sha256": "7e8d74499a444318913734f71a160dbcbaa796cc3e6c22c5c877b1d41b2f9f06"
}
