{
  "_id": "dqa-en-142-c0035",
  "level": 1,
  "novel_id": 142,
  "title": "烟囱别墅之谜",
  "source_file": "data\\raw\\detectiveqa\\novel_data_en\\142-烟囱别墅之谜-阿加莎克里斯蒂.txt",
  "chunk_index": 35,
  "summary": "Anthony and Virginia walk through a rose garden toward a villa, discussing a mysterious man who behaves like a hunting dog and recently provided a piece of paper allegedly dropped by a foreigner, whom Anthony identifies as Lemmon. During their walk, Anthony shares his cynical views on risk-taking and marriage, and confesses his desire to make Virginia like him, noting a sense of \"magic\" from their first meeting on Pound Street.\n\nVirginia notices Constable Butler watching them from the library window. Butler informs them that Professor Woodward has arrived to decode a cipher on a letter. The group observes the red-haired professor through the window; Woodward dismisses the task as simple common sense and announces he has finished decoding the letter marked \"Chimney House.\" After the professor departs, Butler provides Anthony and Virginia with a summary of the decoded Queen's letter.\n\nThe text reveals that an individual identified as \"S\"—whom Anthony identifies as Stapleton—has moved a diamond from its hiding place. The letter contains the cryptic note: \"Richmond, seven straight eight left three right.\" While Anthony and Virginia initially consider if the diamond is in Richmond, Virginia realizes the diamond is likely hidden within the villa behind a Holbein portrait in the dining room, specifically near the portrait of the Earl of Richmond. Butler notes that thieves had previously searched the armor figures beneath the painting, suggesting the numbers in the note might refer to measurements for a secret panel or passage.",
  "summary_whitespace_tokens": 242,
  "start_paragraph_id": 2611,
  "end_paragraph_id": 2686,
  "paragraph_ids": [
    2611,
    2612,
    2613,
    2614,
    2615,
    2616,
    2617,
    2618,
    2619,
    2620,
    2621,
    2622,
    2623,
    2624,
    2625,
    2626,
    2627,
    2628,
    2629,
    2630,
    2631,
    2632,
    2633,
    2634,
    2635,
    2636,
    2637,
    2638,
    2639,
    2640,
    2641,
    2642,
    2643,
    2644,
    2645,
    2646,
    2647,
    2648,
    2649,
    2650,
    2651,
    2652,
    2653,
    2654,
    2655,
    2656,
    2657,
    2658,
    2659,
    2660,
    2661,
    2662,
    2663,
    2664,
    2665,
    2666,
    2667,
    2668,
    2669,
    2670,
    2671,
    2672,
    2673,
    2674,
    2675,
    2676,
    2677,
    2678,
    2679,
    2680,
    2681,
    2682,
    2683,
    2684,
    2685,
    2686
  ],
  "paragraph_doc_ids": [
    "dqa-en-142-p2611",
    "dqa-en-142-p2612",
    "dqa-en-142-p2613",
    "dqa-en-142-p2614",
    "dqa-en-142-p2615",
    "dqa-en-142-p2616",
    "dqa-en-142-p2617",
    "dqa-en-142-p2618",
    "dqa-en-142-p2619",
    "dqa-en-142-p2620",
    "dqa-en-142-p2621",
    "dqa-en-142-p2622",
    "dqa-en-142-p2623",
    "dqa-en-142-p2624",
    "dqa-en-142-p2625",
    "dqa-en-142-p2626",
    "dqa-en-142-p2627",
    "dqa-en-142-p2628",
    "dqa-en-142-p2629",
    "dqa-en-142-p2630",
    "dqa-en-142-p2631",
    "dqa-en-142-p2632",
    "dqa-en-142-p2633",
    "dqa-en-142-p2634",
    "dqa-en-142-p2635",
    "dqa-en-142-p2636",
    "dqa-en-142-p2637",
    "dqa-en-142-p2638",
    "dqa-en-142-p2639",
    "dqa-en-142-p2640",
    "dqa-en-142-p2641",
    "dqa-en-142-p2642",
    "dqa-en-142-p2643",
    "dqa-en-142-p2644",
    "dqa-en-142-p2645",
    "dqa-en-142-p2646",
    "dqa-en-142-p2647",
    "dqa-en-142-p2648",
    "dqa-en-142-p2649",
    "dqa-en-142-p2650",
    "dqa-en-142-p2651",
    "dqa-en-142-p2652",
    "dqa-en-142-p2653",
    "dqa-en-142-p2654",
    "dqa-en-142-p2655",
    "dqa-en-142-p2656",
    "dqa-en-142-p2657",
    "dqa-en-142-p2658",
    "dqa-en-142-p2659",
    "dqa-en-142-p2660",
    "dqa-en-142-p2661",
    "dqa-en-142-p2662",
    "dqa-en-142-p2663",
    "dqa-en-142-p2664",
    "dqa-en-142-p2665",
    "dqa-en-142-p2666",
    "dqa-en-142-p2667",
    "dqa-en-142-p2668",
    "dqa-en-142-p2669",
    "dqa-en-142-p2670",
    "dqa-en-142-p2671",
    "dqa-en-142-p2672",
    "dqa-en-142-p2673",
    "dqa-en-142-p2674",
    "dqa-en-142-p2675",
    "dqa-en-142-p2676",
    "dqa-en-142-p2677",
    "dqa-en-142-p2678",
    "dqa-en-142-p2679",
    "dqa-en-142-p2680",
    "dqa-en-142-p2681",
    "dqa-en-142-p2682",
    "dqa-en-142-p2683",
    "dqa-en-142-p2684",
    "dqa-en-142-p2685",
    "dqa-en-142-p2686"
  ],
  "source_whitespace_tokens": 1564,
  "source_character_count": 8970,
  "source_sha256": "e2c71ddf28875f44e9fc41e6163fbb26a4794f43a6df5e1fd3a77e4e8459ae94",
  "request_sha256": "945e7f236390cec7b1ac8aa979f9cb1b498d29d87e03bf8fbd3aeb5d77d82351",
  "model": "gemma-4-26b-a4b-it",
  "temperature": 0.2,
  "seed": 42,
  "max_output_tokens": 5000,
  "prompt_version": "detectiveqa-summary-pass2-v1.1-fair",
  "pass2_method": "previous_pass2_current_pass1_global_pass1",
  "pass1_prompt_version": "detectiveqa-summary-v1.2",
  "pass1_model": "gemma-4-26b-a4b-it",
  "pass1_summary_sha256": "33c33d8137bd85d724273d2e4e4074a5af01a172602bf16ccc83ce98b06de5b9",
  "previous_pass2_summary_sha256": "80d95ce3951d17322d987a950e5d3944eeb575091916716e09d9640298afa91a",
  "global_pass1_summary_sha256": "d3a64dc6a0d44d4a50115f080a9cdbb4ab5ec297bf4aac65f838486d96f6403e"
}
