{
  "_id": "dqa-en-252-c0011",
  "level": 1,
  "novel_id": 252,
  "title": "奉命谋杀",
  "source_file": "data\\raw\\detectiveqa\\novel_data_en\\252-奉命谋杀-阿加莎克里斯蒂.txt",
  "chunk_index": 11,
  "summary": "Arthur Calgary interviews Mollie Craig, the former wife of Jack Agglesden, to discuss the circumstances surrounding Jack's arrest for the murder of his mother. Mollie describes Jack, whom she nicknamed \"Monkey Face,\" as a charming manipulator. She recounts how he once used her money to bribe the wife of an auto repair shop owner to drop charges against him. As Calgary attempts to clear Jack's name, he finds himself increasingly disgusted by Jack's character. Mollie admits that while Jack claimed he did not intend to kill his mother, he did hit her with a poker during an attempt to get money to avoid prison. She believes Jack's aggressive nature and financial desperation led to the incident, expressing confusion when Calgary suggests Jack might be innocent.\n\nMollie explains that Jack kept their marriage secret to hide her from his upper-class family, claiming his mother would attempt to control her. She recalls a visit to the Agglesden home where a housekeeper refused to acknowledge her as Jack's wife. During that visit, a man named Mr. Aggles offered her a weekly allowance, which she continues to accept despite the disapproval of her current husband, Joe. Joe, who works in the power department, had previously warned Mollie against Jack. Mollie notes that Joe provided a sizable check as a wedding gift for her current marriage, hoping it would be more successful than her previous one.",
  "summary_whitespace_tokens": 231,
  "start_paragraph_id": 635,
  "end_paragraph_id": 677,
  "paragraph_ids": [
    635,
    636,
    637,
    638,
    639,
    640,
    641,
    642,
    643,
    644,
    645,
    646,
    647,
    648,
    649,
    650,
    651,
    652,
    653,
    654,
    655,
    656,
    657,
    658,
    659,
    660,
    661,
    662,
    663,
    664,
    665,
    666,
    667,
    668,
    669,
    670,
    671,
    672,
    673,
    674,
    675,
    676,
    677
  ],
  "paragraph_doc_ids": [
    "dqa-en-252-p635",
    "dqa-en-252-p636",
    "dqa-en-252-p637",
    "dqa-en-252-p638",
    "dqa-en-252-p639",
    "dqa-en-252-p640",
    "dqa-en-252-p641",
    "dqa-en-252-p642",
    "dqa-en-252-p643",
    "dqa-en-252-p644",
    "dqa-en-252-p645",
    "dqa-en-252-p646",
    "dqa-en-252-p647",
    "dqa-en-252-p648",
    "dqa-en-252-p649",
    "dqa-en-252-p650",
    "dqa-en-252-p651",
    "dqa-en-252-p652",
    "dqa-en-252-p653",
    "dqa-en-252-p654",
    "dqa-en-252-p655",
    "dqa-en-252-p656",
    "dqa-en-252-p657",
    "dqa-en-252-p658",
    "dqa-en-252-p659",
    "dqa-en-252-p660",
    "dqa-en-252-p661",
    "dqa-en-252-p662",
    "dqa-en-252-p663",
    "dqa-en-252-p664",
    "dqa-en-252-p665",
    "dqa-en-252-p666",
    "dqa-en-252-p667",
    "dqa-en-252-p668",
    "dqa-en-252-p669",
    "dqa-en-252-p670",
    "dqa-en-252-p671",
    "dqa-en-252-p672",
    "dqa-en-252-p673",
    "dqa-en-252-p674",
    "dqa-en-252-p675",
    "dqa-en-252-p676",
    "dqa-en-252-p677"
  ],
  "source_whitespace_tokens": 1623,
  "source_character_count": 8572,
  "source_sha256": "f724c9229f0cb83343bb8abf1196d58bf737457e98e323eef0cd930a6accebd5",
  "request_sha256": "6c58503f66d4edaec15bb4eab82d0a2b2ce8ba67c04c69729b2522961d55d9b5",
  "model": "gemma-4-26b-a4b-it",
  "temperature": 0.2,
  "seed": 42,
  "max_output_tokens": 5000,
  "prompt_version": "detectiveqa-summary-pass2-v1.1-fair",
  "pass2_method": "previous_pass2_current_pass1_global_pass1",
  "pass1_prompt_version": "detectiveqa-summary-v1.2",
  "pass1_model": "gemma-4-26b-a4b-it",
  "pass1_summary_sha256": "ab29b5c678a6a3a09311a403e5b9c53076fc55b6332e71969723d6aac8986eab",
  "previous_pass2_summary_sha256": "25a15056ce07ca1547277e82fd61e367f7c3772ddff706ac74eddda8db9a89f4",
  "global_pass1_summary_sha256": "6d72a8e7a2a6b7483b8da68f3abc8d22a8098556ded6846168ae1b3d43f2d0e6"
}
