{
  "_id": "dqa-en-252-c0039",
  "level": 1,
  "novel_id": 252,
  "title": "奉命谋杀",
  "source_file": "data\\raw\\detectiveqa\\novel_data_en\\252-奉命谋杀-阿加莎克里斯蒂.txt",
  "chunk_index": 39,
  "summary": "Philip and Gwendolyn discuss the possibility of marriage, though Gwendolyn expresses bitterness and resentment toward Rachel Agar, noting that Leo might be forced to remain Rachel's husband.\n\nIn a separate scene, Tina visits the well-tended grave of Mrs. Aigle in a new cemetery. While she is placing carnations on the tombstone, Mickey arrives. Mickey reveals he is leaving for a job at an oil company in three weeks and wanted to say goodbye to his mother to apologize for his past lack of appreciation and his previous unkindness toward her. During their conversation, Mickey denies killing his mother, a suspicion he believes Tina holds.\n\nTina then reveals that she was at Sunset Point on the night of the death. She explains that while she was walking back to her car, she heard two people whispering. One person specified a time between seven and seven-thirty and told the other not to mess up, followed by a response of \"You can trust me\" and a final comment that \"everything will be wonderful\" afterward. Tina cannot identify the voices but suspects it may have been a man and a woman. She suggests the conspirators could be Leo and Gwendolyn, or perhaps Hurst and someone else, but she explicitly rules out Philip. Tina also mentions seeing a shadow walk quickly past her and hearing a car start, noting that the figure could have been Mickey due to his height and build. Mickey insists he is not the killer and urges Tina to get into his car so he can drive her to Sunny Corner.",
  "summary_whitespace_tokens": 260,
  "start_paragraph_id": 2340,
  "end_paragraph_id": 2432,
  "paragraph_ids": [
    2340,
    2341,
    2342,
    2343,
    2344,
    2345,
    2346,
    2347,
    2348,
    2349,
    2350,
    2351,
    2352,
    2353,
    2354,
    2355,
    2356,
    2357,
    2358,
    2359,
    2360,
    2361,
    2362,
    2363,
    2364,
    2365,
    2366,
    2367,
    2368,
    2369,
    2370,
    2371,
    2372,
    2373,
    2374,
    2375,
    2376,
    2377,
    2378,
    2379,
    2380,
    2381,
    2382,
    2383,
    2384,
    2385,
    2386,
    2387,
    2388,
    2389,
    2390,
    2391,
    2392,
    2393,
    2394,
    2395,
    2396,
    2397,
    2398,
    2399,
    2400,
    2401,
    2402,
    2403,
    2404,
    2405,
    2406,
    2407,
    2408,
    2409,
    2410,
    2411,
    2412,
    2413,
    2414,
    2415,
    2416,
    2417,
    2418,
    2419,
    2420,
    2421,
    2422,
    2423,
    2424,
    2425,
    2426,
    2427,
    2428,
    2429,
    2430,
    2431,
    2432
  ],
  "paragraph_doc_ids": [
    "dqa-en-252-p2340",
    "dqa-en-252-p2341",
    "dqa-en-252-p2342",
    "dqa-en-252-p2343",
    "dqa-en-252-p2344",
    "dqa-en-252-p2345",
    "dqa-en-252-p2346",
    "dqa-en-252-p2347",
    "dqa-en-252-p2348",
    "dqa-en-252-p2349",
    "dqa-en-252-p2350",
    "dqa-en-252-p2351",
    "dqa-en-252-p2352",
    "dqa-en-252-p2353",
    "dqa-en-252-p2354",
    "dqa-en-252-p2355",
    "dqa-en-252-p2356",
    "dqa-en-252-p2357",
    "dqa-en-252-p2358",
    "dqa-en-252-p2359",
    "dqa-en-252-p2360",
    "dqa-en-252-p2361",
    "dqa-en-252-p2362",
    "dqa-en-252-p2363",
    "dqa-en-252-p2364",
    "dqa-en-252-p2365",
    "dqa-en-252-p2366",
    "dqa-en-252-p2367",
    "dqa-en-252-p2368",
    "dqa-en-252-p2369",
    "dqa-en-252-p2370",
    "dqa-en-252-p2371",
    "dqa-en-252-p2372",
    "dqa-en-252-p2373",
    "dqa-en-252-p2374",
    "dqa-en-252-p2375",
    "dqa-en-252-p2376",
    "dqa-en-252-p2377",
    "dqa-en-252-p2378",
    "dqa-en-252-p2379",
    "dqa-en-252-p2380",
    "dqa-en-252-p2381",
    "dqa-en-252-p2382",
    "dqa-en-252-p2383",
    "dqa-en-252-p2384",
    "dqa-en-252-p2385",
    "dqa-en-252-p2386",
    "dqa-en-252-p2387",
    "dqa-en-252-p2388",
    "dqa-en-252-p2389",
    "dqa-en-252-p2390",
    "dqa-en-252-p2391",
    "dqa-en-252-p2392",
    "dqa-en-252-p2393",
    "dqa-en-252-p2394",
    "dqa-en-252-p2395",
    "dqa-en-252-p2396",
    "dqa-en-252-p2397",
    "dqa-en-252-p2398",
    "dqa-en-252-p2399",
    "dqa-en-252-p2400",
    "dqa-en-252-p2401",
    "dqa-en-252-p2402",
    "dqa-en-252-p2403",
    "dqa-en-252-p2404",
    "dqa-en-252-p2405",
    "dqa-en-252-p2406",
    "dqa-en-252-p2407",
    "dqa-en-252-p2408",
    "dqa-en-252-p2409",
    "dqa-en-252-p2410",
    "dqa-en-252-p2411",
    "dqa-en-252-p2412",
    "dqa-en-252-p2413",
    "dqa-en-252-p2414",
    "dqa-en-252-p2415",
    "dqa-en-252-p2416",
    "dqa-en-252-p2417",
    "dqa-en-252-p2418",
    "dqa-en-252-p2419",
    "dqa-en-252-p2420",
    "dqa-en-252-p2421",
    "dqa-en-252-p2422",
    "dqa-en-252-p2423",
    "dqa-en-252-p2424",
    "dqa-en-252-p2425",
    "dqa-en-252-p2426",
    "dqa-en-252-p2427",
    "dqa-en-252-p2428",
    "dqa-en-252-p2429",
    "dqa-en-252-p2430",
    "dqa-en-252-p2431",
    "dqa-en-252-p2432"
  ],
  "source_whitespace_tokens": 1514,
  "source_character_count": 8418,
  "source_sha256": "09480c3dae69a1c232212d40e006b503f1a2e0494a0b667308aa39d4925071ed",
  "request_sha256": "bf65a26fe2680718018ff39ad1a98ad1c934266e391f87ff56cbe0649ae99ef3",
  "model": "gemma-4-26b-a4b-it",
  "temperature": 0.2,
  "seed": 42,
  "max_output_tokens": 5000,
  "prompt_version": "detectiveqa-summary-v1.2"
}
