{
  "_id": "dqa-en-140-c0014",
  "level": 1,
  "novel_id": 140,
  "title": "沉睡谋杀案",
  "source_file": "data\\raw\\detectiveqa\\novel_data_en\\140-沉睡谋杀案-阿加莎克里斯蒂.txt",
  "chunk_index": 14,
  "summary": "Dr. Penrose informs Gwendolyn Reed that her father, Colonel Kelvin Haldi, committed suicide by overdosing on sleeping pills he had secretly stockpiled. Dr. Penrose clarifies that while Haldi suffered from delusions—including the belief that his wife, Helen, was poisoning him—he was not a murderer. The doctor suggests Haldi’s conviction that he had killed his wife stemmed from a psychological desire for punishment after finding a note from her stating she was leaving him. Dr. Penrose provides Gwendolyn with an old black notebook containing Haldi's case notes, which had been preserved by a Dr. McQuail.\n\nWhile traveling back to London by train, Gwendolyn reads the notebook. The entries reveal Haldi's mental instability and his suspicion that Helen was hiding something or had a lover. He records a memory of finding a note in the dining room followed by \"darkness,\" leading him to believe he strangled her. He expresses a desire to end his life to prevent scandal and protect Gweneth, whom he mentions is in New Zealand. Gwendolyn, moved to tears, notices a headline in a passenger's newspaper asking, \"Who is the man in her life?\" which mirrors the suspicions in the diary.\n\nThe narrative shifts to Miss Marple, who is walking through a seafront square and entering an embroidery shop on Fore Street. While purchasing turquoise yarn, Miss Marple engages in polite conversation with the shop assistants, noting that she has not been to the area in nineteen years.",
  "summary_whitespace_tokens": 239,
  "start_paragraph_id": 771,
  "end_paragraph_id": 819,
  "paragraph_ids": [
    771,
    772,
    773,
    774,
    775,
    776,
    777,
    778,
    779,
    780,
    781,
    782,
    783,
    784,
    785,
    786,
    787,
    788,
    789,
    790,
    791,
    792,
    793,
    794,
    795,
    796,
    797,
    798,
    799,
    800,
    801,
    802,
    803,
    804,
    805,
    806,
    807,
    808,
    809,
    810,
    811,
    812,
    813,
    814,
    815,
    816,
    817,
    818,
    819
  ],
  "paragraph_doc_ids": [
    "dqa-en-140-p771",
    "dqa-en-140-p772",
    "dqa-en-140-p773",
    "dqa-en-140-p774",
    "dqa-en-140-p775",
    "dqa-en-140-p776",
    "dqa-en-140-p777",
    "dqa-en-140-p778",
    "dqa-en-140-p779",
    "dqa-en-140-p780",
    "dqa-en-140-p781",
    "dqa-en-140-p782",
    "dqa-en-140-p783",
    "dqa-en-140-p784",
    "dqa-en-140-p785",
    "dqa-en-140-p786",
    "dqa-en-140-p787",
    "dqa-en-140-p788",
    "dqa-en-140-p789",
    "dqa-en-140-p790",
    "dqa-en-140-p791",
    "dqa-en-140-p792",
    "dqa-en-140-p793",
    "dqa-en-140-p794",
    "dqa-en-140-p795",
    "dqa-en-140-p796",
    "dqa-en-140-p797",
    "dqa-en-140-p798",
    "dqa-en-140-p799",
    "dqa-en-140-p800",
    "dqa-en-140-p801",
    "dqa-en-140-p802",
    "dqa-en-140-p803",
    "dqa-en-140-p804",
    "dqa-en-140-p805",
    "dqa-en-140-p806",
    "dqa-en-140-p807",
    "dqa-en-140-p808",
    "dqa-en-140-p809",
    "dqa-en-140-p810",
    "dqa-en-140-p811",
    "dqa-en-140-p812",
    "dqa-en-140-p813",
    "dqa-en-140-p814",
    "dqa-en-140-p815",
    "dqa-en-140-p816",
    "dqa-en-140-p817",
    "dqa-en-140-p818",
    "dqa-en-140-p819"
  ],
  "source_whitespace_tokens": 1515,
  "source_character_count": 8615,
  "source_sha256": "ba580e43874ac4e7315136cb84a533eca316214c78d2e65dc1430cb4d8ccebfa",
  "request_sha256": "419cfc0a804112f14a819a0cc9cda020554a40c76a689d4ced1dc1b7af492bfe",
  "model": "gemma-4-26b-a4b-it",
  "temperature": 0.2,
  "seed": 42,
  "max_output_tokens": 5000,
  "prompt_version": "detectiveqa-summary-v1.2"
}
