{
  "_id": "dqa-en-151-c0014",
  "level": 1,
  "novel_id": 151,
  "title": "三只瞎老鼠",
  "source_file": "data\\raw\\detectiveqa\\novel_data_en\\151-三只瞎老鼠-阿加莎克里斯蒂.txt",
  "chunk_index": 14,
  "summary": "Mr. Satterthwaite and Mr. Quinn converse over Turkish coffee served by Ali. Mr. Satterthwaite reveals his intention to visit Doveton Kingsburn, a quiet country villa and estate owned by his old friend, Tom Addison. He describes his long history with Tom, who served in the foreign service and married a Spanish woman named Pilar. \n\nMr. Satterthwaite details the family's history: Tom and Pilar had two daughters, Lily and Maria. Maria died in childbirth, leaving behind a daughter named Inez, who lives in the village with her doctor father. Lily married a fighter pilot, Wing Commander Simon Gilliat; they moved to Kenya and had a son, Roland. However, Lily died in a car accident, leaving Roland as an infant. Simon subsequently remarried a widow, and they had a son named Timothy. The two boys, Roland and Timothy, were raised like brothers.\n\nDue to circumstances in Kenya, Simon, his second wife, and the two grown sons eventually returned to England and moved to the Doveton Kingsburn manor to live harmoniously with Tom. Mr. Satterthwaite, who is Lily's godfather, expresses a desire to see Roland, whom he has not seen since the boy was twelve. He notes that Tom is aging and has a limp, but remains content. While Mr. Satterthwaite reflects on the nostalgia of visiting the estate, he admits that one thing worries him. Mr. Quinn maintains an intense interest in the family details, prompting a moment of suspicion from Mr. Satterthwaite.",
  "summary_whitespace_tokens": 241,
  "start_paragraph_id": 1004,
  "end_paragraph_id": 1037,
  "paragraph_ids": [
    1004,
    1005,
    1006,
    1007,
    1008,
    1009,
    1010,
    1011,
    1012,
    1013,
    1014,
    1015,
    1016,
    1017,
    1018,
    1019,
    1020,
    1021,
    1022,
    1023,
    1024,
    1025,
    1026,
    1027,
    1028,
    1029,
    1030,
    1031,
    1032,
    1033,
    1034,
    1035,
    1036,
    1037
  ],
  "paragraph_doc_ids": [
    "dqa-en-151-p1004",
    "dqa-en-151-p1005",
    "dqa-en-151-p1006",
    "dqa-en-151-p1007",
    "dqa-en-151-p1008",
    "dqa-en-151-p1009",
    "dqa-en-151-p1010",
    "dqa-en-151-p1011",
    "dqa-en-151-p1012",
    "dqa-en-151-p1013",
    "dqa-en-151-p1014",
    "dqa-en-151-p1015",
    "dqa-en-151-p1016",
    "dqa-en-151-p1017",
    "dqa-en-151-p1018",
    "dqa-en-151-p1019",
    "dqa-en-151-p1020",
    "dqa-en-151-p1021",
    "dqa-en-151-p1022",
    "dqa-en-151-p1023",
    "dqa-en-151-p1024",
    "dqa-en-151-p1025",
    "dqa-en-151-p1026",
    "dqa-en-151-p1027",
    "dqa-en-151-p1028",
    "dqa-en-151-p1029",
    "dqa-en-151-p1030",
    "dqa-en-151-p1031",
    "dqa-en-151-p1032",
    "dqa-en-151-p1033",
    "dqa-en-151-p1034",
    "dqa-en-151-p1035",
    "dqa-en-151-p1036",
    "dqa-en-151-p1037"
  ],
  "source_whitespace_tokens": 1506,
  "source_character_count": 8388,
  "source_sha256": "caaa760ca17dce6572bb8318d85377ff598c62e30a5a6483e6f2ded39fcfd4c0",
  "request_sha256": "0f8208a3bf7e451a085f285d8e0306d3f64828ddc98a1409057593f882dc38b3",
  "model": "gemma-4-26b-a4b-it",
  "temperature": 0.2,
  "seed": 42,
  "max_output_tokens": 5000,
  "prompt_version": "detectiveqa-summary-v1.2"
}
