{
  "_id": "dqa-en-219-c0039",
  "level": 1,
  "novel_id": 219,
  "title": "字母袖扣谋杀案",
  "source_file": "data\\raw\\detectiveqa\\novel_data_en\\219-字母袖扣谋杀案-苏菲·汉娜.txt",
  "chunk_index": 39,
  "summary": "Hercule Poirot confronts Jane Hobbs regarding her knowledge of the murders of Harriet Sipper, Ada Gransbury, and Richard Nigg. Poirot notes that Jane previously claimed justice would only be served when she was dead, a statement made at 7:45, despite the bodies not being discovered at the Browns Hotel until 8:10. Overwhelmed by guilt, Jane confesses the truth behind the tragedy involving Patrick and Frances Ives.\n\nJane reveals that while serving Patrick at Jesus College, Cambridge, she fell in love with him. Driven by jealousy after overhearing Patrick's affection for Nancy Dunn, Jane fabricated a lie to Harriet Sipper, claiming Patrick's words to Nancy were actually intended for the late William Dunn. Harriet spread this rumor through the village, supported by Alice and Richard, leading to the social ruin of the Ives. Although Nancy attempted to defend Patrick by clarifying there was no physical affair, the village's condemnation led Frances to commit suicide, followed by Patrick. Jane also reveals that Dr. Ambrose Flavard burned the Ives' wills to protect their reputation from the villagers' zealotry.\n\nFollowing Patrick's death, Jane moved to London with the help of Sam Kidd. Fifteen years later, she received a letter from Richard Nigg, who obtained her London address from Dr. Flavard. Richard visited her, asking for her help to rectify the mistakes of the past.",
  "summary_whitespace_tokens": 220,
  "start_paragraph_id": 1828,
  "end_paragraph_id": 1856,
  "paragraph_ids": [
    1828,
    1829,
    1830,
    1831,
    1832,
    1833,
    1834,
    1835,
    1836,
    1837,
    1838,
    1839,
    1840,
    1841,
    1842,
    1843,
    1844,
    1845,
    1846,
    1847,
    1848,
    1849,
    1850,
    1851,
    1852,
    1853,
    1854,
    1855,
    1856
  ],
  "paragraph_doc_ids": [
    "dqa-en-219-p1828",
    "dqa-en-219-p1829",
    "dqa-en-219-p1830",
    "dqa-en-219-p1831",
    "dqa-en-219-p1832",
    "dqa-en-219-p1833",
    "dqa-en-219-p1834",
    "dqa-en-219-p1835",
    "dqa-en-219-p1836",
    "dqa-en-219-p1837",
    "dqa-en-219-p1838",
    "dqa-en-219-p1839",
    "dqa-en-219-p1840",
    "dqa-en-219-p1841",
    "dqa-en-219-p1842",
    "dqa-en-219-p1843",
    "dqa-en-219-p1844",
    "dqa-en-219-p1845",
    "dqa-en-219-p1846",
    "dqa-en-219-p1847",
    "dqa-en-219-p1848",
    "dqa-en-219-p1849",
    "dqa-en-219-p1850",
    "dqa-en-219-p1851",
    "dqa-en-219-p1852",
    "dqa-en-219-p1853",
    "dqa-en-219-p1854",
    "dqa-en-219-p1855",
    "dqa-en-219-p1856"
  ],
  "source_whitespace_tokens": 1542,
  "source_character_count": 8437,
  "source_sha256": "522d705045f9cc8943a1ebe31245998f5826d997717484934c7d4de879d3776a",
  "request_sha256": "a25747d8f261c02cfad260281c3772a11d9afabef9042f415b1fc690ba859c95",
  "model": "gemma-4-26b-a4b-it",
  "temperature": 0.2,
  "seed": 42,
  "max_output_tokens": 5000,
  "prompt_version": "detectiveqa-summary-v1.2"
}
