{
  "_id": "dqa-en-27-c0008",
  "level": 1,
  "novel_id": 27,
  "title": "埃及十字架之谜",
  "source_file": "data\\raw\\detectiveqa\\novel_data_en\\27-埃及十字架之谜-埃勒里奎因.txt",
  "chunk_index": 8,
  "summary": "A decapitated male corpse is found hanging from a totem pole, which Professor Yadley identifies as either a genuine Native American totem or a convincing fake. The victim, identified as millionaire carpet importer Thomas Braid, is a middle-aged man with a large beer belly. His body is bound by the arms and feet to the eagle's wings of the pole, and a bloodstained hole exists just below the eagle's beak where his head should be.\n\nOfficer Vaughn explains that the body was discovered at 7:30 AM by Fox, a driver and gardener, while walking near the main house. Jonah Lincoln, the general manager of Braid's company, was present at the scene and maintained control until police arrived. It is noted that Megalas, another associate, is currently at sea.\n\nAs the body is lowered for an autopsy by the medical examiner, Dr. Rumson, the district attorney notes that a bloody chair was found in a nearby gazebo, suggesting the killer used it to reach the nine-foot height. Officer Vance presents Ellery with a red wooden chess piece found in the sandy ground near the totem pole. Upon examining the corpse on the grass, Dr. Rumson discovers a circular red spot on Braid's right palm that resembles paint or dye rather than blood. Ellery realizes the spot is an impression left by the chess piece. Detective Vane confirms this by placing the red chess piece on the victim's palm, where it fits the mark perfectly.",
  "summary_whitespace_tokens": 243,
  "start_paragraph_id": 412,
  "end_paragraph_id": 456,
  "paragraph_ids": [
    412,
    413,
    414,
    415,
    416,
    417,
    418,
    419,
    420,
    421,
    422,
    423,
    424,
    425,
    426,
    427,
    428,
    429,
    430,
    431,
    432,
    433,
    434,
    435,
    436,
    437,
    438,
    439,
    440,
    441,
    442,
    443,
    444,
    445,
    446,
    447,
    448,
    449,
    450,
    451,
    452,
    453,
    454,
    455,
    456
  ],
  "paragraph_doc_ids": [
    "dqa-en-27-p412",
    "dqa-en-27-p413",
    "dqa-en-27-p414",
    "dqa-en-27-p415",
    "dqa-en-27-p416",
    "dqa-en-27-p417",
    "dqa-en-27-p418",
    "dqa-en-27-p419",
    "dqa-en-27-p420",
    "dqa-en-27-p421",
    "dqa-en-27-p422",
    "dqa-en-27-p423",
    "dqa-en-27-p424",
    "dqa-en-27-p425",
    "dqa-en-27-p426",
    "dqa-en-27-p427",
    "dqa-en-27-p428",
    "dqa-en-27-p429",
    "dqa-en-27-p430",
    "dqa-en-27-p431",
    "dqa-en-27-p432",
    "dqa-en-27-p433",
    "dqa-en-27-p434",
    "dqa-en-27-p435",
    "dqa-en-27-p436",
    "dqa-en-27-p437",
    "dqa-en-27-p438",
    "dqa-en-27-p439",
    "dqa-en-27-p440",
    "dqa-en-27-p441",
    "dqa-en-27-p442",
    "dqa-en-27-p443",
    "dqa-en-27-p444",
    "dqa-en-27-p445",
    "dqa-en-27-p446",
    "dqa-en-27-p447",
    "dqa-en-27-p448",
    "dqa-en-27-p449",
    "dqa-en-27-p450",
    "dqa-en-27-p451",
    "dqa-en-27-p452",
    "dqa-en-27-p453",
    "dqa-en-27-p454",
    "dqa-en-27-p455",
    "dqa-en-27-p456"
  ],
  "source_whitespace_tokens": 1510,
  "source_character_count": 8533,
  "source_sha256": "8a6473d39caa4c3034cabea753145c5863c7b489f29ec60b041c3ac0a231214e",
  "request_sha256": "55562152defaf81cc244a83030ae1cec157915168d10506a16e791eabbec3ef0",
  "model": "gemma-4-26b-a4b-it",
  "temperature": 0.2,
  "seed": 42,
  "max_output_tokens": 5000,
  "prompt_version": "detectiveqa-summary-v1.2"
}
