{
  "_id": "dqa-en-198-c0006",
  "level": 1,
  "novel_id": 198,
  "title": "ABC谋杀案",
  "source_file": "data\\raw\\detectiveqa\\novel_data_en\\198-ABC谋杀案-阿加莎克里斯蒂.txt",
  "chunk_index": 6,
  "summary": "Hercule Poirot and Hastings interview Mrs. Fowler, a neighbor of the deceased Mrs. Ascher, paying her five pounds for her information. Mrs. Fowler reveals that Mrs. Ascher was a private person who suffered from the financial demands and behavior of her alcoholic husband, Franz Ascher. Mrs. Fowler notes that Franz was a \"beast\" who had previously threatened to ruin her. When Poirot asks about anonymous \"ABC\" letters or train timetables, Mrs. Fowler denies seeing any. She also suggests that Franz likely hid himself well to avoid being caught for the murder, noting the house lacks a back door.\n\nFollowing this, they encounter Inspector Glen, who expresses frustration over the investigation. Glen reports that witnesses saw various groups of strangers near the shop—including tall, shifty men and short, bearded men—but no one saw a group of masked men with revolvers. No one has reported seeing Mr. Ascher.\n\nThe pair then interviews Mr. James Patrick, a thin, precise bank clerk who claims to be the last person to see Mrs. Ascher alive. Patrick states he arrived at her shop at 5:30 PM, a time he remembers by checking his watch against the church bell. He claims to know nothing of Mrs. Ascher’s personal life or her husband's alcoholism. While leaving, Poirot notices an \"ABC\" British Rail timetable on a shelf in Patrick's home and takes it under the pretense of checking train schedules. Finally, they attempt to speak with Albert Riddle, a hostile railway worker, but he refuses to cooperate, stating he has already told the police everything.",
  "summary_whitespace_tokens": 256,
  "start_paragraph_id": 449,
  "end_paragraph_id": 519,
  "paragraph_ids": [
    449,
    450,
    451,
    452,
    453,
    454,
    455,
    456,
    457,
    458,
    459,
    460,
    461,
    462,
    463,
    464,
    465,
    466,
    467,
    468,
    469,
    470,
    471,
    472,
    473,
    474,
    475,
    476,
    477,
    478,
    479,
    480,
    481,
    482,
    483,
    484,
    485,
    486,
    487,
    488,
    489,
    490,
    491,
    492,
    493,
    494,
    495,
    496,
    497,
    498,
    499,
    500,
    501,
    502,
    503,
    504,
    505,
    506,
    507,
    508,
    509,
    510,
    511,
    512,
    513,
    514,
    515,
    516,
    517,
    518,
    519
  ],
  "paragraph_doc_ids": [
    "dqa-en-198-p449",
    "dqa-en-198-p450",
    "dqa-en-198-p451",
    "dqa-en-198-p452",
    "dqa-en-198-p453",
    "dqa-en-198-p454",
    "dqa-en-198-p455",
    "dqa-en-198-p456",
    "dqa-en-198-p457",
    "dqa-en-198-p458",
    "dqa-en-198-p459",
    "dqa-en-198-p460",
    "dqa-en-198-p461",
    "dqa-en-198-p462",
    "dqa-en-198-p463",
    "dqa-en-198-p464",
    "dqa-en-198-p465",
    "dqa-en-198-p466",
    "dqa-en-198-p467",
    "dqa-en-198-p468",
    "dqa-en-198-p469",
    "dqa-en-198-p470",
    "dqa-en-198-p471",
    "dqa-en-198-p472",
    "dqa-en-198-p473",
    "dqa-en-198-p474",
    "dqa-en-198-p475",
    "dqa-en-198-p476",
    "dqa-en-198-p477",
    "dqa-en-198-p478",
    "dqa-en-198-p479",
    "dqa-en-198-p480",
    "dqa-en-198-p481",
    "dqa-en-198-p482",
    "dqa-en-198-p483",
    "dqa-en-198-p484",
    "dqa-en-198-p485",
    "dqa-en-198-p486",
    "dqa-en-198-p487",
    "dqa-en-198-p488",
    "dqa-en-198-p489",
    "dqa-en-198-p490",
    "dqa-en-198-p491",
    "dqa-en-198-p492",
    "dqa-en-198-p493",
    "dqa-en-198-p494",
    "dqa-en-198-p495",
    "dqa-en-198-p496",
    "dqa-en-198-p497",
    "dqa-en-198-p498",
    "dqa-en-198-p499",
    "dqa-en-198-p500",
    "dqa-en-198-p501",
    "dqa-en-198-p502",
    "dqa-en-198-p503",
    "dqa-en-198-p504",
    "dqa-en-198-p505",
    "dqa-en-198-p506",
    "dqa-en-198-p507",
    "dqa-en-198-p508",
    "dqa-en-198-p509",
    "dqa-en-198-p510",
    "dqa-en-198-p511",
    "dqa-en-198-p512",
    "dqa-en-198-p513",
    "dqa-en-198-p514",
    "dqa-en-198-p515",
    "dqa-en-198-p516",
    "dqa-en-198-p517",
    "dqa-en-198-p518",
    "dqa-en-198-p519"
  ],
  "source_whitespace_tokens": 1538,
  "source_character_count": 8595,
  "source_sha256": "fbce07278ef53a009c8a982303855e17f2afbab4ef36a7a2a2b79aa8babe2137",
  "request_sha256": "e365deefdd55b4516139a67fbd5892085b6ca5e6445c8298cf34bb331d352598",
  "model": "gemma-4-26b-a4b-it",
  "temperature": 0.2,
  "seed": 42,
  "max_output_tokens": 5000,
  "prompt_version": "detectiveqa-summary-v1.2"
}
